flake8_import_restrictions/__init__.py
flake8_import_restrictions/checker.py
flake8_import_restrictions/imports_submodule.py
flake8_import_restrictions-2.1.dist-info/LICENSE
flake8_import_restrictions-2.1.dist-info/METADATA
flake8_import_restrictions-2.1.dist-info/WHEEL
flake8_import_restrictions-2.1.dist-info/entry_points.txt
flake8_import_restrictions-2.1.dist-info/top_level.txt
flake8_import_restrictions-2.1.dist-info/RECORD
