Metadata-Version: 2.1
Name: flake8-import-restrictions
Version: 2.1
Summary: A flake8 plugin used to disallow certain forms of imports.
Home-page: https://github.com/atollk/flake8-import-restrictions
Author: Andreas Tollkötter
License: MIT
Keywords: flake8,import
Classifier: Framework :: Flake8
Classifier: Intended Audience :: Developers
Classifier: License :: OSI Approved :: MIT License
Classifier: Natural Language :: English
Classifier: Programming Language :: Python :: 3 :: Only
Classifier: Programming Language :: Python :: 3
Classifier: Programming Language :: Python :: 3.8
Classifier: Programming Language :: Python :: 3.9
Classifier: Programming Language :: Python :: 3.10
Classifier: Programming Language :: Python :: 3.11
Classifier: Programming Language :: Python :: 3.12
Requires-Python: >=3.8
License-File: LICENSE
